Metadata-Version: 1.0
Name: rsdist
Version: 0.1
Summary: Gaussian distributions
Home-page: UNKNOWN
Author: reham galal
Author-email: rehamgalal1@outlook.com
License: UNKNOWN
Platform: UNKNOWN
